Metadata-Version: 2.1
Name: mqdm
Version: 1.1.0
Summary: cross-process progress bars
Requires-Dist: rich
Requires-Dist: pdbr
Provides-Extra: test
Requires-Dist: fire; extra == "test"
